{
    "917962584": {
        "balance": 6.783936313559321,
        "banned": false,
        "name": "Tammam",
        "username": "tammam7941",
        "total_deposited": 0.423728813559322,
        "is_admin": true
    },
    "8238110323": {
        "balance": 100000256.62064803,
        "banned": false,
        "name": "Æ Â Ł ìí",
        "username": "Nexstoxmena",
        "total_deposited": 0.0,
        "is_admin": false
    },
    "889194151": {
        "balance": 5.4932949,
        "banned": false,
        "name": "AHMAD",
        "username": "Whitestorenc",
        "total_deposited": 14.46
    },
    "972830090": {
        "balance": 0.0,
        "banned": false,
        "name": "Hussein",
        "username": "HuSsein0991",
        "total_deposited": 0.0
    },
    "6102508532": {
        "balance": 43.9866525,
        "banned": false,
        "name": ".",
        "username": null,
        "total_deposited": 0.0,
        "is_admin": false
    }
}